LICENSE
LICENSE.txt
MANIFEST.in
README.md
setup.py
bztt_requests/__init__.py
bztt_requests/__version__.py
bztt_requests/_internal_utils.py
bztt_requests/adapters.py
bztt_requests/api.py
bztt_requests/auth.py
bztt_requests/certs.py
bztt_requests/compat.py
bztt_requests/cookies.py
bztt_requests/exceptions.py
bztt_requests/help.py
bztt_requests/hooks.py
bztt_requests/models.py
bztt_requests/packages.py
bztt_requests/sessions.py
bztt_requests/status_codes.py
bztt_requests/structures.py
bztt_requests/utils.py
bztt_requests.egg-info/PKG-INFO
bztt_requests.egg-info/SOURCES.txt
bztt_requests.egg-info/dependency_links.txt
bztt_requests.egg-info/requires.txt
bztt_requests.egg-info/top_level.txt