Metadata-Version: 2.1
Name: bztt-requests
Version: 0.0.2
Summary: bztt_requests
Home-page: https://github.com/
Author: ls_psz
Author-email: 1160201372@qq.com
License: MIT
Platform: UNKNOWN
Classifier: License :: OSI Approved :: MIT License
Classifier: Programming Language :: Python
Classifier: Programming Language :: Python :: 3
Classifier: Programming Language :: Python :: 3.6
Classifier: Programming Language :: Python :: Implementation :: CPython
Classifier: Programming Language :: Python :: Implementation :: PyPy
Requires-Python: >=3.6.0
